<?xml version="1.0" encoding="utf-8"?>
<I c="LootActions" i="action" m="interactions.utils.loot" n="loot_Reaction_Pet_AgeUp_Happy_targeted" s="166963">
  <L n="loot_actions">
    <V t="reaction">
      <U n="reaction">
        <V n="mixer_reaction" t="enabled">
          <U n="enabled">
            <T n="affordance">166964<!--MixerInteraction: reaction_Mixer_Pet_AgeUp_targeted_thought--></T>
            <V n="affordance_target" t="enabled" />
          </U>
        </V>
        <V n="si_reaction" t="enabled">
          <U n="enabled">
            <T n="affordance">166962<!--SuperInteraction: reactions_Pet_AgeUp_Happy_targetedSI--></T>
            <E n="affordance_priority">High</E>
            <V n="affordance_run_priority" t="disabled" />
          </U>
        </V>
      </U>
    </V>
  </L>
</I>