<?xml version="1.0" encoding="utf-8"?>
<I c="SituationGoalActor" i="situation_goal" m="situations.situation_goal_actor" n="situationGoalActor_ExploreTheNight_NightOwlTrait" s="302054">
  <T n="_cooldown">0</T>
  <V n="_display_data" t="enabled">
    <U n="enabled">
      <V n="instance_display_icon" t="enabled">
        <T p="InGame\UI\Icons\Headlines\Final\headline_NightOwl.png" n="enabled">2f7d0004:00000000:39dc98a00887a8c0</T>
      </V>
      <V n="instance_display_name" t="enabled">
        <T n="enabled">0xA227614<!--String: "Acquire the Night Owl Trait"--></T>
      </V>
      <V n="instance_display_tooltip" t="enabled">
        <T n="enabled">0x435AA4<!--String: "Buy the Night Owl Trait from the Rewards Store in the Aspiration Panel.\n\nThis Trait will help your Sim gain skills faster at night!"--></T>
      </V>
    </U>
  </V>
  <V n="_goal_test" t="buff">
    <U n="buff">
      <V n="whitelist" t="enabled">
        <L n="enabled">
          <T>32425<!--Buff: Buff_Trait_NightOwl--></T>
        </L>
      </V>
    </U>
  </V>
  <L n="_scenario_roles">
    <T>273416<!--ScenarioRole: scenarioRole_PrimarySim--></T>
  </L>
  <T n="_score">0</T>
  <T p="" n="audio_sting_on_complete" />
</I>