<?xml version="1.0" encoding="utf-8"?>
<I c="Aspiration" i="aspiration" m="aspirations.aspiration_tuning" n="aspiration_Deviance_B4" s="25374">
  <T n="display_name">0x95C30307<!--String: "Chief of Mischief"--></T>
  <T n="do_not_register_events_on_load">True</T>
  <L n="objectives">
    <T>25298<!--Objective: objective_Asp_Deviance_B4_1--></T>
    <T>25315<!--Objective: objective_Asp_Deviance_B4_2--></T>
    <T>25300<!--Objective: objective_Asp_Deviance_B4_3--></T>
  </L>
  <V n="screen_slam" t="enabled">
    <V n="enabled" t="reference">
      <T n="reference">74869<!--ScreenSlam: Deviance_ChiefOfMischief_TrackComplete--></T>
    </V>
  </V>
</I>