<?xml version="1.0" encoding="utf-8"?>
<I c="ObjectivelessWhimSet" i="aspiration" m="whims.whim_set" n="whimset_HasTraitHotheaded" s="34797">
  <T n="priority">10</T>
  <T n="whim_reason">0x8F7A8E97<!--String: "(From Being Hot-Headed)"--></T>
  <L n="whims">
    <U>
      <T n="whim">279479<!--Whim: want_Kick_Trashcan--></T>
    </U>
    <U>
      <T n="whim">280261<!--Whim: want_RileUp--></T>
    </U>
    <U>
      <T n="whim">282343<!--Whim: want_Win_CompetitiveGame--></T>
    </U>
  </L>
</I>