<?xml version="1.0" encoding="utf-8"?>
<I c="ObjectivelessWhimSet" i="aspiration" m="whims.whim_set" n="whimset_HasTraitInsane" s="34798">
  <T n="priority">1</T>
  <T n="whim_reason">0x4198DF89<!--String: "(From Being Erratic)"--></T>
  <L n="whims">
    <U>
      <T n="goal">98033<!--SituationGoalObjectInteraction: WhimTalkToSelf--></T>
    </U>
    <U>
      <T n="goal">132251<!--SituationGoalObjectInteraction: whimGoal_MakeAWish--></T>
    </U>
    <U>
      <T n="goal">103298<!--SituationGoalObjectInteraction: WhimTellStoryToSelf--></T>
    </U>
    <U>
      <T n="goal">177812<!--SituationGoalObjectInteraction: Whim_ChaseBirdFlock--></T>
    </U>
    <U>
      <T n="goal">190636<!--SituationGoalObjectInteraction: whimGoal_StruckByLightning--></T>
    </U>
  </L>
</I>