<?xml version="1.0" encoding="utf-8"?>
<I c="CasPreferenceCategory" i="cas_preference_category" m="cas.cas_preference_category" n="PreferenceCategory_Color" s="259880">
  <V n="_display_data" t="optional_display_mixin">
    <U n="optional_display_mixin">
      <V n="instance_display_description" t="enabled_display_description">
        <T n="enabled_display_description">0x37D2B98D<!--String: "Color"--></T>
      </V>
      <V n="instance_display_icon" t="enabled_display_icon">
        <T n="enabled_display_icon" p="InGame\UI\Icons\Headlines\Final\headline_ColorPalette.png">2f7d0004:00000000:94422b98760856b2</T>
      </V>
      <V n="instance_display_name" t="enabled_display_name">
        <T n="enabled_display_name">0x9AA5C01E<!--String: "Color"--></T>
      </V>
      <V n="instance_display_tooltip" t="enabled_display_tooltip">
        <T n="enabled_display_tooltip">0x49FC6CEA<!--String: "Everybody needs a favorite Color! Sims can Ask other Sims about their Favorite Color, and Child Sims can take it a step further."--></T>
      </V>
    </U>
  </V>
</I>