<?xml version="1.0" encoding="utf-8"?>
<I c="TunableTestedGreetingTargeted" i="snippet" m="interactions.social.greeting_socials.greetings" n="tunableTestedGreetingTargeted_ProperTrait" s="252020">
  <L n="tests">
    <L>
      <V t="posture">
        <U n="posture">
          <L n="prohibited_postures">
            <T>39398<!--MobilePosture: posture_Swim--></T>
          </L>
        </U>
      </V>
      <V t="posture">
        <U n="posture">
          <L n="prohibited_postures">
            <T>39398<!--MobilePosture: posture_Swim--></T>
          </L>
          <E n="subject">TargetSim</E>
        </U>
      </V>
      <V t="buff">
        <U n="buff">
          <L n="blacklist">
            <T>123741<!--Buff: Buff_NoGreetings--></T>
          </L>
        </U>
      </V>
      <V t="buff">
        <U n="buff">
          <L n="blacklist">
            <T>123741<!--Buff: Buff_NoGreetings--></T>
          </L>
          <E n="subject">TargetSim</E>
        </U>
      </V>
      <V t="trait">
        <U n="trait">
          <L n="whitelist_traits">
            <T>251970<!--Trait: trait_Proper--></T>
          </L>
        </U>
      </V>
    </L>
  </L>
  <V n="tests_or_greeting" t="greeting">
    <U n="greeting">
      <U n="si">
        <T n="affordance">250754<!--SocialSuperInteraction: nonTouching_Unpaired_Greeting_Bow--></T>
      </U>
    </U>
  </V>
</I>