<?xml version="1.0" encoding="utf-8"?>
<I c="TestSetInstance" i="snippet" m="event_testing.tests" n="testSet_Gardening_AllowMaintenance_Basic" s="259735">
  <L n="test">
    <L>
      <V t="object_definition_criteria">
        <U n="object_definition_criteria">
          <V n="identity_test" t="tags">
            <U n="tags">
              <L n="tag_set">
                <E>Func_GiantCrops_Plant</E>
              </L>
              <E n="test_type">CONTAINS_NO_TAGS_IN_SET</E>
            </U>
          </V>
        </U>
      </V>
      <V t="state_white_black">
        <U n="state_white_black">
          <U n="states">
            <V n="blacklist" t="specify">
              <U n="specify">
                <L n="blacklist">
                  <T>15211<!--ObjectStateValue: GardeningQuality_00_Wild--></T>
                  <T>39330<!--CommodityBasedObjectStateValue: PlantEvolution_0_Death--></T>
                </L>
              </U>
            </V>
          </U>
        </U>
      </V>
    </L>
    <L>
      <V t="object_definition_criteria">
        <U n="object_definition_criteria">
          <V n="identity_test" t="tags">
            <U n="tags">
              <L n="tag_set">
                <E>Func_GiantCrops_Plant</E>
              </L>
            </U>
          </V>
        </U>
      </V>
      <V t="state">
        <U n="state">
          <E n="operator">NOTEQUAL</E>
          <T n="value">260954<!--CommodityBasedObjectStateValue: state_GiantCrops_Plant_Status_Withered--></T>
        </U>
      </V>
    </L>
  </L>
</I>