<?xml version="1.0" encoding="utf-8"?>
<I c="PortalData" i="snippet" m="snippets" n="portalData_poolLadder" s="178743">
  <U n="value">
    <V n="required_flags" t="enabled">
      <L n="enabled">
        <E>PoolPortal</E>
        <E>REQUIRE_NO_CARRY</E>
        <E>SPECIES_HUMAN</E>
      </L>
    </V>
    <V n="traversal_cost" t="fixed_cost">
      <U n="fixed_cost">
        <T n="cost">10</T>
      </U>
    </V>
    <V n="traversal_type" t="posture_change">
      <U n="posture_change">
        <V n="_outfit_change" t="enabled">
          <V n="enabled" t="for_reason">
            <U n="for_reason">
              <V n="on_entry" t="enabled">
                <E n="enabled">Category_Swimwear</E>
              </V>
              <V n="on_exit" t="enabled">
                <E n="enabled">ExitPool</E>
              </V>
            </U>
          </V>
        </V>
        <T n="posture_end">39398<!--MobilePosture: posture_Swim--></T>
        <T n="posture_start">15537<!--MobilePosture: posture_Stand--></T>
        <V n="routing_surface_end" t="specified">
          <U n="specified">
            <E n="surface_type">SURFACETYPE_POOL</E>
          </U>
        </V>
        <V n="routing_surface_start" t="specified">
          <U n="specified">
            <E n="surface_type">SURFACETYPE_WORLD</E>
          </U>
        </V>
      </U>
    </V>
  </U>
</I>