<?xml version="1.0" encoding="utf-8"?>
<I c="LootActions" i="action" m="interactions.utils.loot" n="lootActions_CottageLiving_NotebookEntry_Egg" s="266671">
  <L n="loot_actions">
    <V t="create_notebook_entry">
      <U n="create_notebook_entry">
        <V n="notebook_entry" t="create_entry_from_participant_definition">
          <U n="create_entry_from_participant_definition">
            <T n="reference_notebook_entry">266375<!--NotebookEntryCountryItem: notebookEntryCountryItem_Egg--></T>
          </U>
        </V>
        <L n="tests">
          <L>
            <V t="object_definition_criteria">
              <U n="object_definition_criteria">
                <V n="identity_test" t="definition_id">
                  <U n="definition_id">
                    <T n="actual_object">266633</T>
                  </U>
                </V>
              </U>
            </V>
          </L>
        </L>
      </U>
    </V>
    <V t="create_notebook_entry">
      <U n="create_notebook_entry">
        <V n="notebook_entry" t="create_entry_from_participant_definition">
          <U n="create_entry_from_participant_definition">
            <T n="reference_notebook_entry">266449<!--NotebookEntryCountryItem: notebookEntryCountryItem_Egg_Gold--></T>
          </U>
        </V>
        <L n="tests">
          <L>
            <V t="object_definition_criteria">
              <U n="object_definition_criteria">
                <V n="identity_test" t="definition_id">
                  <U n="definition_id">
                    <T n="actual_object">272308</T>
                  </U>
                </V>
              </U>
            </V>
          </L>
        </L>
      </U>
    </V>
    <V t="create_notebook_entry">
      <U n="create_notebook_entry">
        <V n="notebook_entry" t="create_entry_from_participant_definition">
          <U n="create_entry_from_participant_definition">
            <T n="reference_notebook_entry">266448<!--NotebookEntryCountryItem: notebookEntryCountryItem_Egg_Chocolate--></T>
          </U>
        </V>
        <L n="tests">
          <L>
            <V t="object_definition_criteria">
              <U n="object_definition_criteria">
                <V n="identity_test" t="definition_id">
                  <U n="definition_id">
                    <T n="actual_object">272309</T>
                  </U>
                </V>
              </U>
            </V>
          </L>
        </L>
      </U>
    </V>
    <V t="create_notebook_entry">
      <U n="create_notebook_entry">
        <V n="notebook_entry" t="create_entry_from_participant_definition">
          <U n="create_entry_from_participant_definition">
            <T n="reference_notebook_entry">266451<!--NotebookEntryCountryItem: notebookEntryCountryItem_Egg_Obsidian--></T>
          </U>
        </V>
        <L n="tests">
          <L>
            <V t="object_definition_criteria">
              <U n="object_definition_criteria">
                <V n="identity_test" t="definition_id">
                  <U n="definition_id">
                    <T n="actual_object">272310</T>
                  </U>
                </V>
              </U>
            </V>
          </L>
        </L>
      </U>
    </V>
    <V t="create_notebook_entry">
      <U n="create_notebook_entry">
        <V n="notebook_entry" t="create_entry_from_participant_definition">
          <U n="create_entry_from_participant_definition">
            <T n="reference_notebook_entry">266447<!--NotebookEntryCountryItem: notebookEntryCountryItem_Egg_Blue--></T>
          </U>
        </V>
        <L n="tests">
          <L>
            <V t="object_definition_criteria">
              <U n="object_definition_criteria">
                <V n="identity_test" t="definition_id">
                  <U n="definition_id">
                    <T n="actual_object">272311</T>
                  </U>
                </V>
              </U>
            </V>
          </L>
        </L>
      </U>
    </V>
    <V t="create_notebook_entry">
      <U n="create_notebook_entry">
        <V n="notebook_entry" t="create_entry_from_participant_definition">
          <U n="create_entry_from_participant_definition">
            <T n="reference_notebook_entry">266450<!--NotebookEntryCountryItem: notebookEntryCountryItem_Egg_Green--></T>
          </U>
        </V>
        <L n="tests">
          <L>
            <V t="object_definition_criteria">
              <U n="object_definition_criteria">
                <V n="identity_test" t="definition_id">
                  <U n="definition_id">
                    <T n="actual_object">272312</T>
                  </U>
                </V>
              </U>
            </V>
          </L>
        </L>
      </U>
    </V>
    <V t="create_notebook_entry">
      <U n="create_notebook_entry">
        <V n="notebook_entry" t="create_entry_from_participant_definition">
          <U n="create_entry_from_participant_definition">
            <T n="reference_notebook_entry">266452<!--NotebookEntryCountryItem: notebookEntryCountryItem_Egg_Orange--></T>
          </U>
        </V>
        <L n="tests">
          <L>
            <V t="object_definition_criteria">
              <U n="object_definition_criteria">
                <V n="identity_test" t="definition_id">
                  <U n="definition_id">
                    <T n="actual_object">272313</T>
                  </U>
                </V>
              </U>
            </V>
          </L>
        </L>
      </U>
    </V>
    <V t="create_notebook_entry">
      <U n="create_notebook_entry">
        <V n="notebook_entry" t="create_entry_from_participant_definition">
          <U n="create_entry_from_participant_definition">
            <T n="reference_notebook_entry">266453<!--NotebookEntryCountryItem: notebookEntryCountryItem_Egg_Rainbow--></T>
          </U>
        </V>
        <L n="tests">
          <L>
            <V t="object_definition_criteria">
              <U n="object_definition_criteria">
                <V n="identity_test" t="definition_id">
                  <U n="definition_id">
                    <T n="actual_object">272314</T>
                  </U>
                </V>
              </U>
            </V>
          </L>
        </L>
      </U>
    </V>
    <V t="create_notebook_entry">
      <U n="create_notebook_entry">
        <V n="notebook_entry" t="create_entry_from_participant_definition">
          <U n="create_entry_from_participant_definition">
            <T n="reference_notebook_entry">270124<!--NotebookEntryCountryItem: notebookEntryCountryItem_Egg_HatchableEgg--></T>
          </U>
        </V>
        <L n="tests">
          <L>
            <V t="object_definition_criteria">
              <U n="object_definition_criteria">
                <V n="identity_test" t="definition_id">
                  <U n="definition_id">
                    <T n="actual_object">284595</T>
                  </U>
                </V>
              </U>
            </V>
          </L>
        </L>
      </U>
    </V>
    <V t="create_notebook_entry">
      <U n="create_notebook_entry">
        <V n="notebook_entry" t="create_entry_from_participant_definition">
          <U n="create_entry_from_participant_definition">
            <T n="reference_notebook_entry">270125<!--NotebookEntryCountryItem: notebookEntryCountryItem_Egg_HatchableGolden--></T>
          </U>
        </V>
        <L n="tests">
          <L>
            <V t="object_definition_criteria">
              <U n="object_definition_criteria">
                <V n="identity_test" t="definition_id">
                  <U n="definition_id">
                    <T n="actual_object">284597</T>
                  </U>
                </V>
              </U>
            </V>
          </L>
        </L>
      </U>
    </V>
    <V t="create_notebook_entry">
      <U n="create_notebook_entry">
        <V n="notebook_entry" t="create_entry_from_participant_definition">
          <U n="create_entry_from_participant_definition">
            <T n="reference_notebook_entry">270126<!--NotebookEntryCountryItem: notebookEntryCountryItem_Egg_HatchableObsidian--></T>
          </U>
        </V>
        <L n="tests">
          <L>
            <V t="object_definition_criteria">
              <U n="object_definition_criteria">
                <V n="identity_test" t="definition_id">
                  <U n="definition_id">
                    <T n="actual_object">284596</T>
                  </U>
                </V>
              </U>
            </V>
          </L>
        </L>
      </U>
    </V>
  </L>
</I>