<?xml version="1.0" encoding="utf-8"?>
<I c="CasStoriesAnswer" i="cas_stories_answer" m="cas.cas_stories_answer" n="casStoriesAnswer_GP07_Strangerville_Q1_Answer_C" s="215962">
  <T n="text">0xF37E4426<!--String: "Nah, everyone loves me."--></T>
  <L n="weightings">
    <U>
      <T n="weight">3</T>
      <V n="weighted_object" t="trait">
        <T n="trait">9322<!--Trait: trait_Cheerful--></T>
      </V>
    </U>
    <U>
      <T n="weight">3</T>
      <V n="weighted_object" t="aspiration_track">
        <T n="aspiration_track">25276<!--AspirationTrack: Track_Popularity_B--></T>
      </V>
    </U>
  </L>
</I>