<?xml version="1.0" encoding="utf-8"?>
<I c="LootActions" i="action" m="interactions.utils.loot" n="loot_Werewolf_Hunt_Rampage" s="299754">
  <L n="loot_actions">
    <V t="object_rewards">
      <U n="object_rewards">
        <L n="object_rewards">
          <U>
            <T n="quantity">1</T>
            <L n="reward_objects">
              <U>
                <V n="quantity" t="specific_amount" />
                <L n="reward">
                  <V t="specify_recipe">
                    <U n="specify_recipe">
                      <T n="recipe">285954<!--Recipe: recipe_Food_Snack_RawSteak--></T>
                    </U>
                  </V>
                </L>
              </U>
            </L>
          </U>
        </L>
        <L n="tests">
          <L>
            <V t="trait">
              <U n="trait">
                <L n="blacklist_traits">
                  <T>132627<!--Trait: trait_Vegetarian--></T>
                </L>
              </U>
            </V>
          </L>
        </L>
      </U>
    </V>
    <V t="object_rewards">
      <U n="object_rewards">
        <L n="object_rewards">
          <U>
            <T n="quantity">1</T>
            <L n="reward_objects">
              <U>
                <V n="quantity" t="specific_amount">
                  <T n="specific_amount">5</T>
                </V>
                <L n="reward">
                  <V t="specify_definition">
                    <U n="specify_definition">
                      <T n="definition">45311</T>
                    </U>
                  </V>
                </L>
              </U>
              <U>
                <V n="quantity" t="specific_amount">
                  <T n="specific_amount">6</T>
                </V>
                <L n="reward">
                  <V t="specify_definition">
                    <U n="specify_definition">
                      <T n="definition">45311</T>
                    </U>
                  </V>
                </L>
              </U>
              <U>
                <V n="quantity" t="specific_amount">
                  <T n="specific_amount">3</T>
                </V>
                <L n="reward">
                  <V t="specify_definition">
                    <U n="specify_definition">
                      <T n="definition">45311</T>
                    </U>
                  </V>
                </L>
              </U>
              <U>
                <V n="quantity" t="specific_amount">
                  <T n="specific_amount">4</T>
                </V>
                <L n="reward">
                  <V t="specify_definition">
                    <U n="specify_definition">
                      <T n="definition">45311</T>
                    </U>
                  </V>
                </L>
              </U>
              <U>
                <V n="quantity" t="specific_amount">
                  <T n="specific_amount">2</T>
                </V>
                <L n="reward">
                  <V t="specify_definition">
                    <U n="specify_definition">
                      <T n="definition">286364</T>
                    </U>
                  </V>
                </L>
              </U>
              <U>
                <V n="quantity" t="specific_amount">
                  <T n="specific_amount">2</T>
                </V>
                <L n="reward">
                  <V t="specify_definition">
                    <U n="specify_definition">
                      <T n="definition">66145</T>
                    </U>
                  </V>
                </L>
              </U>
            </L>
          </U>
        </L>
        <L n="tests">
          <L>
            <V t="trait">
              <U n="trait">
                <L n="whitelist_traits">
                  <T>132627<!--Trait: trait_Vegetarian--></T>
                </L>
              </U>
            </V>
          </L>
        </L>
      </U>
    </V>
    <V t="actions">
      <T n="actions">287173<!--LootActions: loot_WerewolfXP_Med--></T>
    </V>
  </L>
</I>