<?xml version="1.0" encoding="utf-8"?>
<I c="LootActions" i="action" m="interactions.utils.loot" n="loot_HighSchool_Active_NPC_Princiipal_PushCatchTruant" s="277066">
  <L n="loot_actions">
    <V t="reaction">
      <U n="reaction">
        <U n="chance">
          <T n="base_chance">100</T>
        </U>
        <V n="si_reaction" t="enabled">
          <U n="enabled">
            <T n="affordance">277039<!--SocialSuperInteraction: super_Social_HighSchool_Active_NPC_Principal_CatchTruant--></T>
            <E n="affordance_priority">Critical</E>
            <V n="affordance_target" t="enabled">
              <E n="enabled">Actor</E>
            </V>
          </U>
        </V>
        <E n="subject">TargetSim</E>
        <L n="tests">
          <L>
            <V t="buff">
              <U n="buff">
                <L n="blacklist">
                  <T>285599<!--Buff: buff_Role_Highschool_Active_Player_Truant--></T>
                </L>
                <E n="subject">TargetSim</E>
              </U>
            </V>
          </L>
        </L>
      </U>
    </V>
    <V t="reaction">
      <U n="reaction">
        <V n="si_reaction" t="enabled">
          <U n="enabled">
            <T n="affordance">277039<!--SocialSuperInteraction: super_Social_HighSchool_Active_NPC_Principal_CatchTruant--></T>
            <E n="affordance_priority">Critical</E>
            <V n="affordance_target" t="enabled">
              <E n="enabled">TargetSim</E>
            </V>
          </U>
        </V>
        <E n="subject">Actor</E>
        <L n="tests">
          <L>
            <V t="buff">
              <U n="buff">
                <E n="subject">TargetSim</E>
                <V n="whitelist" t="enabled">
                  <L n="enabled">
                    <T>285599<!--Buff: buff_Role_Highschool_Active_Player_Truant--></T>
                  </L>
                </V>
              </U>
            </V>
          </L>
        </L>
      </U>
    </V>
  </L>
</I>