<?xml version="1.0" encoding="utf-8"?>
<I c="SituationDramaNode" i="drama_node" m="drama_scheduler.situation_drama_node" n="situationDramaNode_NPCRelationshipAutonomy_Propose" s="278855">
  <U n="min_and_max_times">
    <T n="lower_bound">0</T>
    <T n="upper_bound">24</T>
  </U>
  <E n="receiver_sim">TargetSim</E>
  <L n="run_tests">
    <L>
      <V t="test_set_reference">
        <T n="test_set_reference">100585<!--TestSetInstance: testSet_RomanceAllowedAge--></T>
      </V>
      <V t="relationship">
        <U n="relationship">
          <U n="prohibited_relationship_bits">
            <L n="match_any">
              <T>15816<!--RelationshipBit: romantic-Engaged--></T>
              <T>15822<!--RelationshipBit: romantic-Married--></T>
            </L>
          </U>
          <U n="relationship_score_interval">
            <T n="lower_bound">85</T>
          </U>
          <T n="track">16651<!--RelationshipTrack: LTR_Romance_Main--></T>
        </U>
      </V>
    </L>
  </L>
  <V n="sender_sim_info" t="participant_type" />
  <V n="sender_sim_info_job" t="enabled">
    <T n="enabled">16182<!--SituationJob: job_visitor--></T>
  </V>
  <E n="sender_sim_info_type">INSTANCED_ALLOWED</E>
  <T n="situation_to_run">278862<!--GreetedNPCVisitingPlayerSituation: situation_NPCRelationshipAutonomy_Propose--></T>
  <V n="time_option" t="schedule">
    <U n="schedule">
      <L n="valid_times">
        <U>
          <U n="days_available">
            <T n="0 SUNDAY">True</T>
            <T n="1 MONDAY">True</T>
            <T n="2 TUESDAY">True</T>
            <T n="3 WEDNESDAY">True</T>
            <T n="4 THURSDAY">True</T>
            <T n="5 FRIDAY">True</T>
            <T n="6 SATURDAY">True</T>
          </U>
          <T n="duration">12</T>
          <U n="start_time">
            <T n="hour">8</T>
          </U>
        </U>
      </L>
    </U>
  </V>
</I>