<?xml version="1.0" encoding="utf-8"?>
<I c="Objective" i="objective" m="event_testing.objective_tuning" n="objective_RunExam" s="170171">
  <V n="objective_test" t="ran_interaction_test">
    <U n="ran_interaction_test">
      <L n="affordances">
        <T>166617<!--SuperInteraction: vet_Surgery_StartExam--></T>
        <T>165474<!--SuperInteraction: vet_ExamObjects_StartExam--></T>
        <T>177020<!--SuperInteraction: vet_ExamObjects_StartExam_Autonomous_SmallPets--></T>
        <T>177018<!--SuperInteraction: vet_ExamObjects_StartExam_SmallPets--></T>
      </L>
    </U>
  </V>
  <T n="resettable">True</T>
</I>