<?xml version="1.0" encoding="utf-8"?>
<I c="BalloonCategory" i="balloon" m="balloon.balloon_category" n="balloonCategories_Movie_Reactions_Frightened" s="129272">
  <T n="balloon_chance">100</T>
  <E n="balloon_type">SPEECH</E>
  <L n="balloons">
    <U>
      <V n="item" t="balloon_icon">
        <U n="balloon_icon">
          <V n="category_icon" t="show_category_icon">
            <V n="show_category_icon" t="resource_key">
              <U n="resource_key">
                <T n="key" p="InSP05\UI\Icons\Headlines\headline_MovieSubIcon.png">2f7d0004:00000000:f7d28ca4cb6f3539</T>
              </U>
            </V>
          </V>
          <V n="icon" t="resource_key">
            <U n="resource_key">
              <T n="key" p="InGame\UI\Icons\Headlines\Final\headline_ghost.png">2f7d0004:00000000:14094b494cd3f93d</T>
            </U>
          </V>
        </U>
      </V>
    </U>
    <U>
      <V n="item" t="balloon_icon">
        <U n="balloon_icon">
          <V n="category_icon" t="show_category_icon">
            <V n="show_category_icon" t="resource_key">
              <U n="resource_key">
                <T n="key" p="InSP05\UI\Icons\Headlines\headline_MovieSubIcon.png">2f7d0004:00000000:f7d28ca4cb6f3539</T>
              </U>
            </V>
          </V>
          <V n="icon" t="resource_key">
            <U n="resource_key">
              <T n="key" p="InGame\UI\Icons\Headlines\Final\headline_gravestone.png">2f7d0004:00000000:7c70ef2a230cf012</T>
            </U>
          </V>
        </U>
      </V>
    </U>
    <U>
      <V n="item" t="balloon_icon">
        <U n="balloon_icon">
          <V n="category_icon" t="show_category_icon">
            <V n="show_category_icon" t="resource_key">
              <U n="resource_key">
                <T n="key" p="InSP05\UI\Icons\Headlines\headline_MovieSubIcon.png">2f7d0004:00000000:f7d28ca4cb6f3539</T>
              </U>
            </V>
          </V>
          <V n="icon" t="resource_key">
            <U n="resource_key">
              <T n="key" p="InGame\UI\Icons\Headlines\Final\headline_Urn.png">2f7d0004:00000000:ca53d1442d508ac1</T>
            </U>
          </V>
        </U>
      </V>
    </U>
    <U>
      <V n="item" t="balloon_icon">
        <U n="balloon_icon">
          <V n="category_icon" t="show_category_icon">
            <V n="show_category_icon" t="resource_key">
              <U n="resource_key">
                <T n="key" p="InSP05\UI\Icons\Headlines\headline_MovieSubIcon.png">2f7d0004:00000000:f7d28ca4cb6f3539</T>
              </U>
            </V>
          </V>
          <V n="icon" t="resource_key">
            <U n="resource_key">
              <T n="key" p="InGame\UI\Icons\Headlines\Final\headline_voodoo.png">2f7d0004:00000000:7dc06723e64d7316</T>
            </U>
          </V>
        </U>
      </V>
    </U>
    <U>
      <V n="item" t="balloon_icon">
        <U n="balloon_icon">
          <V n="category_icon" t="show_category_icon">
            <V n="show_category_icon" t="resource_key">
              <U n="resource_key">
                <T n="key" p="InSP05\UI\Icons\Headlines\headline_MovieSubIcon.png">2f7d0004:00000000:f7d28ca4cb6f3539</T>
              </U>
            </V>
          </V>
          <V n="icon" t="resource_key">
            <U n="resource_key">
              <T n="key" p="InGame\UI\Icons\Headlines\Final\headline_spider.png">2f7d0004:00000000:8d03425662ca3463</T>
            </U>
          </V>
        </U>
      </V>
    </U>
  </L>
</I>