<?xml version="1.0" encoding="utf-8"?>
<I c="SocialSuperInteraction" i="interaction" m="interactions.social.social_super_interaction" n="social_Batuu_Missions_Use_Rep_For_Info" s="240336">
  <V n="_icon" t="participant">
    <U n="participant">
      <L n="participant_type">
        <E>TargetSim</E>
      </L>
    </U>
  </V>
  <L n="_party_size_weight_tuning">
    <U>
      <T n="y">100</T>
    </U>
    <U>
      <T n="x">1</T>
      <T n="y">100</T>
    </U>
    <U>
      <T n="x">2</T>
      <T n="y">50</T>
    </U>
    <U>
      <T n="x">3</T>
      <T n="y">0</T>
    </U>
    <U>
      <T n="x">4</T>
    </U>
  </L>
  <V n="_saveable" t="enabled" />
  <T n="_social_group_type">16390<!--SocialGroup: chat--></T>
  <V n="affordance_to_push_on_target" t="push_affordance">
    <T n="push_affordance">244771<!--SocialSuperInteraction: social_Batuu_Missions_Listen--></T>
  </V>
  <T n="attention_cost">0</T>
  <V n="basic_content" t="one_shot" />
  <L n="basic_extras">
    <V t="loot">
      <U n="loot">
        <L n="loot_list">
          <T>162659<!--LootActions: loot_Commodity_Culling_GhostAdd_target--></T>
        </L>
      </U>
    </V>
    <V t="buff">
      <U n="buff">
        <U n="buff_type">
          <V n="buff_reason" t="enabled">
            <T n="enabled">0x9C09275F<!--String: "(From Being in a social group with at least 3 Sims)"--></T>
          </V>
          <T n="buff_type">125555<!--Buff: buff_Trait_WithMyFriends--></T>
        </U>
        <L n="subject">
          <E>Actor</E>
          <E>SocialGroupSims</E>
          <E>TargetSim</E>
        </L>
        <L n="tests">
          <L>
            <V t="social_group">
              <U n="social_group">
                <V n="threshold" t="enabled">
                  <U n="enabled">
                    <T n="value">3</T>
                  </U>
                </V>
              </U>
            </V>
          </L>
        </L>
      </U>
    </V>
  </L>
  <V n="basic_reserve_object" t="disabled" />
  <T n="category">240789<!--PieMenuCategory: batuu_PieMenuCategory_Batuu--></T>
  <V n="content_score" t="enabled">
    <U n="enabled">
      <T n="base_score">999999999</T>
    </U>
  </V>
  <T n="display_name">0xC3E31245<!--String: "Use Reputation For Information"--></T>
  <U n="display_name_text_tokens">
    <L n="tokens">
      <V t="participant_type">
        <U n="participant_type">
          <V n="objects" t="from_participant">
            <U n="from_participant">
              <E n="participant">Actor</E>
            </U>
          </V>
        </U>
      </V>
      <V t="participant_type">
        <U n="participant_type">
          <V n="objects" t="from_participant">
            <U n="from_participant">
              <E n="participant">Object</E>
            </U>
          </V>
        </U>
      </V>
    </L>
  </U>
  <V n="idle_animation" t="enabled">
    <U n="enabled">
      <T n="factory">11570<!--AnimationElement: Listen_Listen_Looping_basic--></T>
    </U>
  </V>
  <T n="ignore_group_socials">False</T>
  <L n="interaction_category_tags">
    <E>Interaction_SocialSuper</E>
    <E>Interaction_Super</E>
    <E>Interaction_All</E>
    <E>Interaction_SocialAll</E>
    <E>Interaction_Social_Contagious</E>
  </L>
  <T n="invite_in_after_interaction">True</T>
  <U n="listen_animation">
    <T n="factory">11570<!--AnimationElement: Listen_Listen_Looping_basic--></T>
  </U>
  <V n="outcome" t="test_based">
    <U n="test_based">
      <L n="tested_outcomes">
        <U>
          <L n="potential_outcomes">
            <U>
              <U n="outcome">
                <V n="animation_ref" t="enabled">
                  <U n="enabled">
                    <T n="factory">113097<!--AnimationElement: soc_Friendly_NT_Brag_Succeed_basic--></T>
                  </U>
                </V>
                <L n="basic_extras">
                  <V t="notification">
                    <U n="notification">
                      <V n="dialog" t="single">
                        <V n="single" t="literal">
                          <U n="literal">
                            <V n="icon" t="enabled">
                              <V n="enabled" t="participant">
                                <U n="participant">
                                  <L n="participant_type">
                                    <E>TargetSim</E>
                                  </L>
                                </U>
                              </V>
                            </V>
                            <V n="secondary_icon" t="enabled">
                              <V n="enabled" t="participant" />
                            </V>
                            <V n="text" t="variation">
                              <U n="variation">
                                <L n="variations">
                                  <T>0x4F63B9E<!--String: "I'll tell you what I know, but I hope you'll remember this favor."--></T>
                                  <T>0x16F1545A<!--String: "I see. Your status changes things. I'll help you out."--></T>
                                  <T>0xA1387B9D<!--String: "I'll tell you what I know, but I hope you'll remember this favor."--></T>
                                  <T>0x7C4189F6<!--String: "Oh, sorry. I didn't know who you were at first... of course I can tell you what I know."--></T>
                                </L>
                              </U>
                            </V>
                            <E n="visual_type">SPEECH</E>
                          </U>
                        </V>
                      </V>
                    </U>
                  </V>
                  <V t="create_object">
                    <U n="create_object">
                      <V n="creation_data" t="definition">
                        <U n="definition">
                          <T n="definition">250414</T>
                        </U>
                      </V>
                      <V n="location" t="inventory" />
                      <E n="owner_sim">Actor</E>
                      <T n="set_sim_as_owner">True</T>
                    </U>
                  </V>
                </L>
                <L n="loot_list">
                  <T>240532<!--LootActions: loot_Batuu_Missions_Target_Has_Given_Info--></T>
                </L>
              </U>
              <U n="weight">
                <L n="multipliers">
                  <U>
                    <T n="multiplier">2</T>
                    <L n="tests">
                      <L>
                        <V t="test_set_reference">
                          <T n="test_set_reference">244941<!--TestSetInstance: testSet_Batuu_FactionReputation_Resistance_SupporterOrMore--></T>
                        </V>
                      </L>
                    </L>
                  </U>
                </L>
              </U>
            </U>
            <U>
              <U n="outcome">
                <V n="animation_ref" t="enabled">
                  <U n="enabled">
                    <T n="factory">113096<!--AnimationElement: soc_Friendly_NT_Brag_Fail_basic--></T>
                  </U>
                </V>
                <L n="basic_extras">
                  <V t="notification">
                    <U n="notification">
                      <V n="dialog" t="single">
                        <V n="single" t="literal">
                          <U n="literal">
                            <V n="icon" t="enabled">
                              <V n="enabled" t="participant">
                                <U n="participant">
                                  <L n="participant_type">
                                    <E>TargetSim</E>
                                  </L>
                                </U>
                              </V>
                            </V>
                            <V n="secondary_icon" t="enabled">
                              <V n="enabled" t="participant" />
                            </V>
                            <V n="text" t="variation">
                              <U n="variation">
                                <L n="variations">
                                  <T>0x71D9D2E9<!--String: "Big deal. Your 'reputation' means nothing to me."--></T>
                                  <T>0x19AF58D3<!--String: "Name dropping won't get me to compromise my integrity."--></T>
                                  <T>0x15EB28BC<!--String: "Your status won't get you special treatment from me."--></T>
                                  <T>0xB7C08AB8<!--String: "I've never heard of you. Your self-proclaimed reputation means nothing to me."--></T>
                                </L>
                              </U>
                            </V>
                            <E n="visual_type">SPEECH</E>
                          </U>
                        </V>
                      </V>
                    </U>
                  </V>
                </L>
              </U>
            </U>
          </L>
          <L n="tests">
            <L>
              <V t="trait">
                <U n="trait">
                  <E n="subject">TargetSim</E>
                  <L n="whitelist_traits">
                    <T>233326<!--Trait: trait_Batuu_Resistance_Identifier--></T>
                  </L>
                </U>
              </V>
            </L>
          </L>
        </U>
        <U>
          <L n="potential_outcomes">
            <U>
              <U n="outcome">
                <V n="animation_ref" t="enabled">
                  <U n="enabled">
                    <T n="factory">113097<!--AnimationElement: soc_Friendly_NT_Brag_Succeed_basic--></T>
                  </U>
                </V>
                <L n="basic_extras">
                  <V t="notification">
                    <U n="notification">
                      <V n="dialog" t="single">
                        <V n="single" t="literal">
                          <U n="literal">
                            <V n="icon" t="enabled">
                              <V n="enabled" t="participant">
                                <U n="participant">
                                  <L n="participant_type">
                                    <E>TargetSim</E>
                                  </L>
                                </U>
                              </V>
                            </V>
                            <V n="secondary_icon" t="enabled">
                              <V n="enabled" t="participant" />
                            </V>
                            <V n="text" t="variation">
                              <U n="variation">
                                <L n="variations">
                                  <T>0xD7C5604C<!--String: "Oh...I did not realize the extent of your deeds. I suppose I can tell you what I know."--></T>
                                  <T>0x83CA0629<!--String: "Oh...I did not realize the extent of your deeds. I suppose I can tell you what I know."--></T>
                                  <T>0x3B1A88E3<!--String: "Having a well-known ally could be beneficial. I suppose I can let you in on some things."--></T>
                                  <T>0x66DDF434<!--String: "Your name does ring a bell. I will tell you what I know, but you will be wise to remember this favor."--></T>
                                </L>
                              </U>
                            </V>
                            <E n="visual_type">SPEECH</E>
                          </U>
                        </V>
                      </V>
                    </U>
                  </V>
                  <V t="create_object">
                    <U n="create_object">
                      <V n="creation_data" t="definition">
                        <U n="definition">
                          <T n="definition">250414</T>
                        </U>
                      </V>
                      <V n="location" t="inventory" />
                      <E n="owner_sim">Actor</E>
                      <T n="set_sim_as_owner">True</T>
                    </U>
                  </V>
                </L>
                <L n="loot_list">
                  <T>240532<!--LootActions: loot_Batuu_Missions_Target_Has_Given_Info--></T>
                </L>
              </U>
              <U n="weight">
                <L n="multipliers">
                  <U>
                    <T n="multiplier">2</T>
                    <L n="tests">
                      <L>
                        <V t="test_set_reference">
                          <T n="test_set_reference">244943<!--TestSetInstance: testSet_Batuu_FactionReputation_FirstOrder_GreaterOrEqual_Rank+1--></T>
                        </V>
                      </L>
                    </L>
                  </U>
                </L>
              </U>
            </U>
            <U>
              <U n="outcome">
                <V n="animation_ref" t="enabled">
                  <U n="enabled">
                    <T n="factory">113096<!--AnimationElement: soc_Friendly_NT_Brag_Fail_basic--></T>
                  </U>
                </V>
                <L n="basic_extras">
                  <V t="notification">
                    <U n="notification">
                      <V n="dialog" t="single">
                        <V n="single" t="literal">
                          <U n="literal">
                            <V n="icon" t="enabled">
                              <V n="enabled" t="participant">
                                <U n="participant">
                                  <L n="participant_type">
                                    <E>TargetSim</E>
                                  </L>
                                </U>
                              </V>
                            </V>
                            <V n="secondary_icon" t="enabled">
                              <V n="enabled" t="participant" />
                            </V>
                            <V n="text" t="variation">
                              <U n="variation">
                                <L n="variations">
                                  <T>0x71D9D2E9<!--String: "Big deal. Your 'reputation' means nothing to me."--></T>
                                  <T>0xA4F4F712<!--String: "Is this a confession? Are you trying to get arrested?"--></T>
                                  <T>0x2A1ED5EA<!--String: "Is your name supposed to impress me?"--></T>
                                  <T>0xCBF8956F<!--String: "I do not care who you are or what you have done. You are not getting anything from me."--></T>
                                </L>
                              </U>
                            </V>
                            <E n="visual_type">SPEECH</E>
                          </U>
                        </V>
                      </V>
                    </U>
                  </V>
                </L>
              </U>
            </U>
          </L>
          <L n="tests">
            <L>
              <V t="trait">
                <U n="trait">
                  <E n="subject">TargetSim</E>
                  <L n="whitelist_traits">
                    <T>233327<!--Trait: trait_Batuu_FirstOrder_Identifier--></T>
                  </L>
                </U>
              </V>
            </L>
          </L>
        </U>
        <U>
          <L n="potential_outcomes">
            <U>
              <U n="outcome">
                <V n="animation_ref" t="enabled">
                  <U n="enabled">
                    <T n="factory">113097<!--AnimationElement: soc_Friendly_NT_Brag_Succeed_basic--></T>
                  </U>
                </V>
                <L n="basic_extras">
                  <V t="notification">
                    <U n="notification">
                      <V n="dialog" t="single">
                        <V n="single" t="literal">
                          <U n="literal">
                            <V n="icon" t="enabled">
                              <V n="enabled" t="participant">
                                <U n="participant">
                                  <L n="participant_type">
                                    <E>TargetSim</E>
                                  </L>
                                </U>
                              </V>
                            </V>
                            <V n="secondary_icon" t="enabled">
                              <V n="enabled" t="participant" />
                            </V>
                            <V n="text" t="variation">
                              <U n="variation">
                                <L n="variations">
                                  <T>0x700C03B9<!--String: "Of course I can tell you what I know. I hope we can help each other out in the future..."--></T>
                                  <T>0x26B18AB8<!--String: "Sorry, I didn't recognize you. No disrespect! Of course I can share what I know."--></T>
                                  <T>0x78DD9A43<!--String: "I've heard of you. Perhaps I can share something..."--></T>
                                  <T>0x543F4F10<!--String: "Of course I can tell you what I know. I hope we can help each other out in the future..."--></T>
                                </L>
                              </U>
                            </V>
                            <E n="visual_type">SPEECH</E>
                          </U>
                        </V>
                      </V>
                    </U>
                  </V>
                  <V t="create_object">
                    <U n="create_object">
                      <V n="creation_data" t="definition">
                        <U n="definition">
                          <T n="definition">250414</T>
                        </U>
                      </V>
                      <V n="location" t="inventory" />
                      <E n="owner_sim">Actor</E>
                      <T n="set_sim_as_owner">True</T>
                    </U>
                  </V>
                </L>
                <L n="loot_list">
                  <T>240532<!--LootActions: loot_Batuu_Missions_Target_Has_Given_Info--></T>
                </L>
              </U>
              <U n="weight">
                <L n="multipliers">
                  <U>
                    <T n="multiplier">2</T>
                    <L n="tests">
                      <L>
                        <V t="test_set_reference">
                          <T n="test_set_reference">244942<!--TestSetInstance: testSet_Batuu_FactionReputation_Scoundrel_GreaterOrEqual_Rank+1--></T>
                        </V>
                      </L>
                    </L>
                  </U>
                </L>
              </U>
            </U>
            <U>
              <U n="outcome">
                <V n="animation_ref" t="enabled">
                  <U n="enabled">
                    <T n="factory">113096<!--AnimationElement: soc_Friendly_NT_Brag_Fail_basic--></T>
                  </U>
                </V>
                <L n="basic_extras">
                  <V t="notification">
                    <U n="notification">
                      <V n="dialog" t="single">
                        <V n="single" t="literal">
                          <U n="literal">
                            <V n="icon" t="enabled">
                              <V n="enabled" t="participant">
                                <U n="participant">
                                  <L n="participant_type">
                                    <E>TargetSim</E>
                                  </L>
                                </U>
                              </V>
                            </V>
                            <V n="secondary_icon" t="enabled">
                              <V n="enabled" t="participant" />
                            </V>
                            <V n="text" t="variation">
                              <U n="variation">
                                <L n="variations">
                                  <T>0x71D9D2E9<!--String: "Big deal. Your 'reputation' means nothing to me."--></T>
                                  <T>0xCD2979B6<!--String: "If you're so big and important, why are you asking me for help?"--></T>
                                  <T>0x9DB80F1F<!--String: "Big deal. Your 'reputation' means nothing to me."--></T>
                                  <T>0xB2CC31AC<!--String: "High status or not, whoever you are, you're a pest."--></T>
                                </L>
                              </U>
                            </V>
                            <E n="visual_type">SPEECH</E>
                          </U>
                        </V>
                      </V>
                    </U>
                  </V>
                </L>
              </U>
            </U>
          </L>
          <L n="tests">
            <L>
              <V t="trait">
                <U n="trait">
                  <E n="subject">TargetSim</E>
                  <L n="whitelist_traits">
                    <T>233344<!--Trait: trait_Batuu_Scoundrel_Identifier--></T>
                  </L>
                </U>
              </V>
            </L>
          </L>
        </U>
        <U>
          <L n="potential_outcomes">
            <U>
              <U n="outcome">
                <V n="animation_ref" t="enabled">
                  <U n="enabled">
                    <T n="factory">113097<!--AnimationElement: soc_Friendly_NT_Brag_Succeed_basic--></T>
                  </U>
                </V>
                <L n="basic_extras">
                  <V t="notification">
                    <U n="notification">
                      <V n="dialog" t="single">
                        <V n="single" t="literal">
                          <U n="literal">
                            <V n="icon" t="enabled">
                              <V n="enabled" t="participant">
                                <U n="participant">
                                  <L n="participant_type">
                                    <E>TargetSim</E>
                                  </L>
                                </U>
                              </V>
                            </V>
                            <V n="secondary_icon" t="enabled">
                              <V n="enabled" t="participant" />
                            </V>
                            <V n="text" t="single">
                              <T n="single">0x914037ED<!--String: "You seem to have the interest of Batuu citizens in mind. I will hand over the information I have as long as you promise not to sell it."--></T>
                            </V>
                            <E n="visual_type">SPEECH</E>
                          </U>
                        </V>
                      </V>
                    </U>
                  </V>
                  <V t="create_object">
                    <U n="create_object">
                      <V n="creation_data" t="definition">
                        <U n="definition">
                          <T n="definition">250414</T>
                        </U>
                      </V>
                      <V n="location" t="inventory" />
                      <E n="owner_sim">Actor</E>
                      <T n="set_sim_as_owner">True</T>
                    </U>
                  </V>
                </L>
                <L n="loot_list">
                  <T>240532<!--LootActions: loot_Batuu_Missions_Target_Has_Given_Info--></T>
                </L>
              </U>
              <U n="weight">
                <L n="multipliers">
                  <U>
                    <T n="multiplier">2</T>
                    <L n="tests">
                      <L>
                        <V t="test_set_reference">
                          <T n="test_set_reference">244942<!--TestSetInstance: testSet_Batuu_FactionReputation_Scoundrel_GreaterOrEqual_Rank+1--></T>
                        </V>
                      </L>
                    </L>
                  </U>
                </L>
              </U>
            </U>
            <U>
              <U n="outcome">
                <V n="animation_ref" t="enabled">
                  <U n="enabled">
                    <T n="factory">113096<!--AnimationElement: soc_Friendly_NT_Brag_Fail_basic--></T>
                  </U>
                </V>
                <L n="basic_extras">
                  <V t="notification">
                    <U n="notification">
                      <V n="dialog" t="single">
                        <V n="single" t="literal">
                          <U n="literal">
                            <V n="icon" t="enabled">
                              <V n="enabled" t="participant">
                                <U n="participant">
                                  <L n="participant_type">
                                    <E>TargetSim</E>
                                  </L>
                                </U>
                              </V>
                            </V>
                            <V n="secondary_icon" t="enabled">
                              <V n="enabled" t="participant" />
                            </V>
                            <V n="text" t="single">
                              <T n="single">0x71D9D2E9<!--String: "Big deal. Your 'reputation' means nothing to me."--></T>
                            </V>
                            <E n="visual_type">SPEECH</E>
                          </U>
                        </V>
                      </V>
                    </U>
                  </V>
                </L>
              </U>
            </U>
          </L>
          <L n="tests">
            <L>
              <V t="trait">
                <U n="trait">
                  <E n="subject">TargetSim</E>
                  <L n="whitelist_traits">
                    <T>235820<!--Trait: trait_Batuu_NPC_Citizen_Identifier--></T>
                  </L>
                </U>
              </V>
            </L>
          </L>
        </U>
      </L>
    </U>
  </V>
  <V n="pie_menu_icon" t="enabled">
    <V n="enabled" t="resource_key">
      <U n="resource_key">
        <T n="key" p="InGP09\UI\Icons\PieMenu\Interactions\icon_pieMenu_orderResist.png">2f7d0004:00000000:a9d99ffeb3c117e7</T>
      </U>
    </V>
  </V>
  <T n="pie_menu_priority">10</T>
  <U n="progress_bar_enabled">
    <T n="bar_enabled">False</T>
  </U>
  <T n="relationship_scoring">True</T>
  <E n="scoring_priority">NORMAL</E>
  <V n="sim_affinity_posture_scoring_data" t="enabled">
    <U n="enabled">
      <L n="my_scoring">
        <U>
          <V n="affinity_strategy" t="relationship_based" />
          <T n="negate_tag">True</T>
          <E n="running_interaction_tag">Sleeping</E>
        </U>
        <U>
          <V n="affinity_strategy" t="avoid" />
          <E n="running_interaction_tag">Very_Loud</E>
        </U>
      </L>
      <L n="my_tags">
        <E>Loud</E>
        <E>Chat</E>
      </L>
    </U>
  </V>
  <T n="subaction_selection_weight">1</T>
  <E n="target_type">TARGET</E>
  <L n="test_globals">
    <V t="sim_info">
      <U n="sim_info">
        <V n="species" t="specified">
          <U n="specified">
            <L n="species">
              <E />
            </L>
          </U>
        </V>
        <E n="who">TargetSim</E>
      </U>
    </V>
    <V t="sim_info">
      <U n="sim_info">
        <V n="ages" t="specified" />
        <V n="species" t="specified">
          <U n="specified">
            <L n="species">
              <E />
            </L>
          </U>
        </V>
        <E n="who">Actor</E>
      </U>
    </V>
    <V t="career_gig_test">
      <U n="career_gig_test">
        <T n="career">231099<!--Career: career_Batuu--></T>
        <V n="test_type" t="specific_gigs">
          <U n="specific_gigs">
            <L n="gigs">
              <T>240632<!--MissionGig: missionGig_Missions_Scoundrel_Repeatable_03--></T>
            </L>
          </U>
        </V>
      </U>
    </V>
    <V t="inventory">
      <U n="inventory">
        <V n="contents_check" t="has_object_with_def">
          <U n="has_object_with_def">
            <T n="definition">250414</T>
          </U>
        </V>
        <U n="required_count">
          <E n="comparison">LESS</E>
          <T n="value">5</T>
        </U>
      </U>
    </V>
    <V t="test_set_reference">
      <T n="test_set_reference">240686<!--TestSetInstance: testSet_Batuu_SNPC_CanTalkTo--></T>
    </V>
    <V t="trait">
      <U n="trait">
        <L n="blacklist_traits">
          <T>240524<!--Trait: trait_Batuu_Mission_Traits_Given_Info--></T>
        </L>
        <E n="subject">TargetSim</E>
        <V n="tooltip" t="enabled">
          <T n="enabled">0x10D41128<!--String: "This person does not have any more information to give."--></T>
        </V>
      </U>
    </V>
  </L>
  <T n="time_overhead">30</T>
  <U n="visual_type_override_data">
    <E n="group_tag">Interaction_Chat</E>
  </U>
</I>