<?xml version="1.0" encoding="utf-8"?>
<I c="AutonomousSimPickerSuperInteraction" i="interaction" m="interactions.base.picker_interaction" n="autonomousSimPicker_TableGame_Cards_PlayWith" s="187986">
  <L n="_false_advertisements">
    <V t="statistic_change">
      <U n="statistic_change">
        <T n="amount">0.4</T>
        <T n="stat">16655<!--Commodity: motive_Fun--></T>
      </U>
    </V>
  </L>
  <V n="_forwarding" t="Forward" />
  <V n="_saveable" t="enabled" />
  <L n="actor_continuation">
    <U>
      <T n="affordance">13131<!--SocialSuperInteraction: cardGame_Playing--></T>
      <E n="target">Object</E>
    </U>
  </L>
  <T n="attention_cost">0.5</T>
  <V n="basic_content" t="one_shot" />
  <V n="content_score" t="disabled" />
  <T n="display_name">0xAD2EE40F<!--String: "Play Cards With"--></T>
  <U n="display_name_text_tokens">
    <L n="tokens">
      <V t="participant_type">
        <U n="participant_type">
          <V n="objects" t="from_participant">
            <U n="from_participant">
              <E n="participant">Actor</E>
            </U>
          </V>
        </U>
      </V>
      <V t="participant_type">
        <U n="participant_type">
          <V n="objects" t="from_participant">
            <U n="from_participant">
              <E n="participant">Object</E>
            </U>
          </V>
        </U>
      </V>
    </L>
  </U>
  <T n="include_uninstantiated_sims">False</T>
  <L n="interaction_category_tags">
    <E>Interaction_Super</E>
    <E>Interaction_All</E>
  </L>
  <L n="picked_continuation">
    <U>
      <T n="affordance">13131<!--SocialSuperInteraction: cardGame_Playing--></T>
      <E n="target">Object</E>
    </U>
  </L>
  <U n="posture_preferences">
    <T n="prefer_clicked_parts">False</T>
  </U>
  <V n="route_start_balloon" t="enabled">
    <U n="enabled">
      <U n="balloon">
        <L n="balloon_choices">
          <U>
            <V n="item" t="balloon_icon">
              <U n="balloon_icon">
                <V n="icon" t="participant">
                  <U n="participant">
                    <L n="participant_type">
                      <E>Object</E>
                    </L>
                  </U>
                </V>
              </U>
            </V>
          </U>
        </L>
        <L n="balloon_target">
          <E>Actor</E>
        </L>
      </U>
    </U>
  </V>
  <E n="scoring_priority">NORMAL</E>
  <V n="sim_filter" t="sim_filter_selected">
    <T n="sim_filter_selected">104072<!--TunableSimFilter: filter_HasMet_CTAYE_AllowGhosts--></T>
  </V>
  <L n="sim_tests">
    <L>
      <V t="test_set_reference">
        <T n="test_set_reference">98254<!--TestSetInstance: testSet_NearbySim_Picker--></T>
      </V>
    </L>
  </L>
  <T n="subaction_selection_weight">1</T>
  <E n="target_type">OBJECT</E>
  <L n="test_globals">
    <V t="sim_info">
      <U n="sim_info">
        <V n="ages" t="specified">
          <L n="specified">
            <E>TEEN</E>
            <E>YOUNGADULT</E>
            <E>ADULT</E>
            <E>ELDER</E>
            <E>CHILD</E>
          </L>
        </V>
        <V n="species" t="specified">
          <U n="specified">
            <L n="species">
              <E />
            </L>
          </U>
        </V>
        <E n="who">Actor</E>
      </U>
    </V>
    <V t="state">
      <U n="state">
        <T n="value">127237<!--ObjectStateValue: gameTable_CardGame--></T>
      </U>
    </V>
    <V t="club_test">
      <U n="club_test">
        <V n="affordance_rule" t="enabled" />
      </U>
    </V>
    <V t="slot_test">
      <U n="slot_test">
        <V n="child_slot" t="by_reference">
          <T n="by_reference">slot_SitChair</T>
        </V>
        <T n="slot_count_required">2</T>
        <V n="slot_test_type" t="has_used_slot" />
        <V n="tooltip" t="enabled">
          <T n="enabled">0x942191F2<!--String: "There are not enough chairs at the table to play a game."--></T>
        </V>
      </U>
    </V>
  </L>
  <T n="time_overhead">30</T>
</I>