<?xml version="1.0" encoding="utf-8"?>
<I c="Broadcaster" i="broadcaster" m="broadcasters.broadcaster" n="broadcaster_Pets_ShowOff" s="166675">
  <L n="constraints">
    <V t="circle">
      <U n="circle">
        <T n="ideal_radius_width">0</T>
        <T n="radius">6</T>
      </U>
    </V>
  </L>
  <L n="effects">
    <V t="affordance">
      <U n="affordance">
        <L n="affordances">
          <U>
            <T n="affordance">166834<!--SuperInteraction: watchForMotive_DogTricks_Clap--></T>
          </U>
        </L>
        <L n="tests">
          <L>
            <V t="sim_info" />
          </L>
          <L>
            <V t="buff">
              <U n="buff">
                <L n="blacklist">
                  <T>170274<!--Buff: buff_Dog_Training_Participant--></T>
                </L>
              </U>
            </V>
          </L>
        </L>
      </U>
    </V>
  </L>
  <V n="frequency" t="on_enter" />
</I>