<?xml version="1.0" encoding="utf-8"?>
<I c="UniversityCourseData" i="university_course_data" m="sims.university.university_tuning" n="university_CourseData_Biology_ClassG" s="219335">
  <L n="classroom_tag">
    <U>
      <T n="key">219731<!--University: ScienceUniversity--></T>
      <L n="value">
        <E>Func_ScienceUniversityShell_Shell2</E>
      </L>
    </U>
    <U>
      <T n="key">219732<!--University: ArtsUniversity--></T>
      <L n="value">
        <E>Func_ArtsUniversityShell_Shell2</E>
      </L>
    </U>
  </L>
  <T n="cost">240</T>
  <U n="course_skill_data">
    <V n="related_skill" t="enabled">
      <T n="enabled">16700<!--Skill: statistic_Skill_AdultMajor_Gardening--></T>
    </V>
  </U>
  <E n="final_requirement_type">EXAM</E>
  <T p="InEP08\UI\Icons\DegreeSystem\Class\DegreeSystem_class_gardening.png" n="icon">2f7d0004:00000000:4be67cd836a93fb3</T>
  <L n="professor_assignment_trait">
    <U>
      <T n="key">219731<!--University: ScienceUniversity--></T>
      <T n="value">224865<!--Trait: trait_Hidden_ProfessorNPC_Course_Science_C--></T>
    </U>
    <U>
      <T n="key">219732<!--University: ArtsUniversity--></T>
      <T n="value">224822<!--Trait: trait_Hidden_ProfessorNPC_Course_Arts_C--></T>
    </U>
  </L>
  <L n="spawn_point_tag">
    <U>
      <T n="key">219731<!--University: ScienceUniversity--></T>
      <L n="value">
        <E>Spawn_ScienceUniversityShell_Shell2</E>
      </L>
    </U>
    <U>
      <T n="key">219732<!--University: ArtsUniversity--></T>
      <L n="value">
        <E>Spawn_ArtsUniversityShell_Shell2</E>
      </L>
    </U>
  </L>
  <L n="university_course_mapping">
    <U>
      <T n="key">219731<!--University: ScienceUniversity--></T>
      <U n="value">
        <T n="course_description">0xB6BC248<!--String: "A large variety of plants nowadays undergo some sort of genetic manipulation. Students will explore early genetic manipulation techniques and talk about what "natural" means in such an environment."--></T>
        <T n="course_name">0x97677AE7<!--String: "Splicing Shoots and Other Genetic Manipulations"--></T>
      </U>
    </U>
    <U>
      <T n="key">219732<!--University: ArtsUniversity--></T>
      <U n="value">
        <T n="course_description">0xA4606010<!--String: "Trees get sick too! With this introduction to forest pathology, students will learn about what tree health means for the ecosystem at large, as well as ways to maintain healthy wooded environments."--></T>
        <T n="course_name">0xB5069B3F<!--String: "Forest Pathology: Think of the Trees!"--></T>
      </U>
    </U>
  </L>
</I>